odoo/addons/l10n_eu_nace/README.rst
odoo/addons/l10n_eu_nace/__init__.py
odoo/addons/l10n_eu_nace/__manifest__.py
odoo/addons/l10n_eu_nace/i18n/ca.po
odoo/addons/l10n_eu_nace/i18n/es.po
odoo/addons/l10n_eu_nace/i18n/it.po
odoo/addons/l10n_eu_nace/i18n/l10n_eu_nace.pot
odoo/addons/l10n_eu_nace/readme/CONTRIBUTORS.md
odoo/addons/l10n_eu_nace/readme/DESCRIPTION.md
odoo/addons/l10n_eu_nace/readme/USAGE.md
odoo/addons/l10n_eu_nace/security/ir.model.access.csv
odoo/addons/l10n_eu_nace/static/description/icon.png
odoo/addons/l10n_eu_nace/static/description/index.html
odoo/addons/l10n_eu_nace/tests/__init__.py
odoo/addons/l10n_eu_nace/tests/test_en_nace_request_results.py
odoo/addons/l10n_eu_nace/tests/test_res_partner_industry_eu_nace_wizard.py
odoo/addons/l10n_eu_nace/wizard/__init__.py
odoo/addons/l10n_eu_nace/wizard/res_partner_industry_eu_nace_wizard.py
odoo/addons/l10n_eu_nace/wizard/res_partner_industry_eu_nace_wizard_view.xml
odoo_addon_l10n_eu_nace-18.0.1.0.1.dist-info/METADATA
odoo_addon_l10n_eu_nace-18.0.1.0.1.dist-info/WHEEL
odoo_addon_l10n_eu_nace-18.0.1.0.1.dist-info/top_level.txt
odoo_addon_l10n_eu_nace-18.0.1.0.1.dist-info/RECORD
