Metadata-Version: 2.1
Name: odoo-addon-l10n_eu_nace
Version: 18.0.1.0.1
Requires-Python: >=3.10
Requires-Dist: odoo-addon-partner_industry_secondary==18.0.*
Requires-Dist: odoo==18.0.*
Summary: European NACE partner categories
Home-page: https://github.com/OCA/community-data-files
License: AGPL-3
Author: =?utf-8?q?Num=C3=A9rigraphe_SARL=2C_Sistheo=2C_Moduon=2C_Odoo_Community_Association_=28OCA=29?=
Author-email: support@odoo-community.org
Classifier: Programming Language :: Python
Classifier: Framework :: Odoo
Classifier: Framework :: Odoo :: 18.0
Classifier: License :: OSI Approved :: GNU Affero General Public License v3
